Metadata-Version: 2.1
Name: Fict
Version: 1.0.1
Summary: File integrity checking tool
Home-page: https://github.com/vhp/fict
Author: Vincent Perricone
Author-email: vhp@fastmail.fm
License: Simplified FreeBSD License
Download-URL: https://github.com/vhp/fict
Platform: linux
